mosaico/__init__.py
mosaico/__main__.py
mosaico/cli.py
mosaico/config.py
mosaico/exceptions.py
mosaico/logging.py
mosaico/media.py
mosaico/py.typed
mosaico/scene.py
mosaico/types.py
mosaico/version.py
mosaico/assets/__init__.py
mosaico/assets/audio.py
mosaico/assets/base.py
mosaico/assets/factory.py
mosaico/assets/image.py
mosaico/assets/reference.py
mosaico/assets/subtitle.py
mosaico/assets/text.py
mosaico/assets/types.py
mosaico/assets/utils.py
mosaico/audio_transcribers/__init__.py
mosaico/audio_transcribers/assemblyai.py
mosaico/audio_transcribers/openai.py
mosaico/audio_transcribers/protocol.py
mosaico/audio_transcribers/transcription.py
mosaico/clip_makers/__init__.py
mosaico/clip_makers/audio.py
mosaico/clip_makers/base.py
mosaico/clip_makers/factory.py
mosaico/clip_makers/image.py
mosaico/clip_makers/protocol.py
mosaico/clip_makers/subtitle.py
mosaico/clip_makers/text.py
mosaico/effects/__init__.py
mosaico/effects/crossfade.py
mosaico/effects/factory.py
mosaico/effects/fade.py
mosaico/effects/pan.py
mosaico/effects/protocol.py
mosaico/effects/types.py
mosaico/effects/zoom.py
mosaico/integrations/__init__.py
mosaico/integrations/base/__init__.py
mosaico/integrations/base/adapters.py
mosaico/integrations/haystack/__init__.py
mosaico/integrations/haystack/media.py
mosaico/integrations/haystack/script_generator.py
mosaico/integrations/langchain/__init__.py
mosaico/integrations/langchain/media.py
mosaico/integrations/langchain/script_generator.py
mosaico/positioning/__init__.py
mosaico/positioning/absolute.py
mosaico/positioning/region.py
mosaico/positioning/relative.py
mosaico/positioning/types.py
mosaico/positioning/utils.py
mosaico/script_generators/__init__.py
mosaico/script_generators/protocol.py
mosaico/script_generators/script.py
mosaico/script_generators/news/__init__.py
mosaico/script_generators/news/generator.py
mosaico/script_generators/news/prompts.py
mosaico/speech_synthesizers/__init__.py
mosaico/speech_synthesizers/elevenlabs.py
mosaico-0.6.0.dist-info/METADATA
mosaico-0.6.0.dist-info/WHEEL
mosaico-0.6.0.dist-info/entry_points.txt
mosaico-0.6.0.dist-info/licenses/LICENSE.md
mosaico-0.6.0.dist-info/RECORD
