Metadata-Version: 2.4
Name: mosaico
Version: 0.6.0
Summary: Open-source video generation framework
Author-email: Leonardo Diegues <leonardo.diegues@grupofolha.com.br>, Lucas Golino <lucas@golinux.space>
License-File: LICENSE.md
Classifier: License :: OSI Approved :: GNU General Public License (GPL)
Classifier: Operating System :: OS Independent
Classifier: Programming Language :: Python :: 3
Classifier: Programming Language :: Python :: 3.10
Classifier: Programming Language :: Python :: 3.11
Classifier: Programming Language :: Python :: 3.12
Classifier: Programming Language :: Python :: 3.13
Classifier: Topic :: Multimedia
Classifier: Topic :: Multimedia :: Sound/Audio :: Sound Synthesis
Classifier: Topic :: Multimedia :: Sound/Audio :: Speech
Classifier: Topic :: Multimedia :: Video :: Non-Linear Editor
Classifier: Topic :: Text Processing :: Fonts
Requires-Python: <3.14,>=3.10
Requires-Dist: audioop-lts>=0.2.1; python_version >= '3.13'
Requires-Dist: deprecated>=1.2.18
Requires-Dist: findsystemfontsfilename>=0.3.0
Requires-Dist: fsspec>=2024.10.0
Requires-Dist: instructor>=1.7.2
Requires-Dist: litellm>=1.61.0
Requires-Dist: moviepy>=2
Requires-Dist: opencv-python>=4.10.0.84
Requires-Dist: pycountry>=24.6.1
Requires-Dist: pydantic
Requires-Dist: pydantic-extra-types>=2.9.0
Requires-Dist: pydantic-settings>=2.8.0
Requires-Dist: pydub>=0.25.1
Requires-Dist: pyyaml
Requires-Dist: tinytag>=1.10.1
Provides-Extra: assemblyai
Requires-Dist: assemblyai>=0.34.0; extra == 'assemblyai'
Provides-Extra: cli
Requires-Dist: click>=8.1.7; extra == 'cli'
Provides-Extra: elevenlabs
Requires-Dist: elevenlabs>=1.9.0; extra == 'elevenlabs'
Provides-Extra: haystack
Requires-Dist: haystack-ai>=2.6.1; extra == 'haystack'
Provides-Extra: langchain
Requires-Dist: langchain>=0.3.7; extra == 'langchain'
Provides-Extra: openai
Requires-Dist: openai>=1.68.0; extra == 'openai'
